mailmap_generator/__init__.py
mailmap_generator/cli.py
mailmap_generator/mailmap.py
mailmap_generator-0.3.1.dist-info/METADATA
mailmap_generator-0.3.1.dist-info/WHEEL
mailmap_generator-0.3.1.dist-info/entry_points.txt
mailmap_generator-0.3.1.dist-info/RECORD
