Metadata-Version: 2.1
Name: mailmap-generator
Version: 0.3.1
Summary: A small command line tool to create git .mailmap files from a commit history.
Home-page: https://gitlab.com/HelgeCPH/mailmap-generator.git
License: AGPL-3.0-or-later
Author: HelgeCPH
Author-email: ropf@itu.dk
Requires-Python: >=3.9,<4.0
Classifier: License :: OSI Approved :: GNU Affero General Public License v3 or later (AGPLv3+)
Classifier: Programming Language :: Python :: 3
Classifier: Programming Language :: Python :: 3.9
Classifier: Programming Language :: Python :: 3.10
Classifier: Programming Language :: Python :: 3.11
Requires-Dist: docopt (>=0.6.2,<0.7.0)
Requires-Dist: pandas (>=1.4.3,<2.0.0)
Project-URL: Documentation, https://gitlab.com/HelgeCPH/mailmap-generator/-/blob/master/README.md
Project-URL: Repository, https://gitlab.com/HelgeCPH/mailmap-generator.git
